elastic_appsearch/__init__.py
elastic_appsearch/elastic_appsearch.py
elastic_appsearch-0.1.0.dist-info/LICENSE.md
elastic_appsearch-0.1.0.dist-info/METADATA
elastic_appsearch-0.1.0.dist-info/WHEEL
elastic_appsearch-0.1.0.dist-info/top_level.txt
elastic_appsearch-0.1.0.dist-info/RECORD
