Metadata-Version: 2.1
Name: elastic-appsearch
Version: 0.1.0
Summary: Elastic App Search API Client
Home-page: https://github.com/sunnysid3up/elastic-appsearch
Author: Sunny Kim
Author-email: sunny.kim@berkeley.edu
Maintainer: Sunny Kim
Maintainer-email: sunny.kim@berkeley.edu
License: MIT
Platform: any
Classifier: Environment :: Web Environment
Classifier: Intended Audience :: Developers
Classifier: License :: OSI Approved :: MIT License
Classifier: Operating System :: OS Independent
Classifier: Programming Language :: Python
Classifier: Programming Language :: Python :: 3
Classifier: Topic :: Software Development :: Libraries :: Python Modules
Requires-Python: >=3
Requires-Dist: requests (>=2.23.0)
